{"Eastern Washington Eagles": "https://college-football-results.com/f/z/eastwash_re.htm", "California-Davis Aggies": "https://college-football-results.com/f/z/caldavis_re.htm", "Montana Grizzlies": "https://college-football-results.com/f/z/montana_re.htm", "Cal Poly Mustangs": "https://college-football-results.com/f/z/polyslo_re.htm", "Montana State Bobcats": "https://college-football-results.com/f/z/montstat_re.htm", "Northern Arizona Lumberjacks": "https://college-football-results.com/f/z/narizona_re.htm", "Weber State Wildcats": "https://college-football-results.com/f/z/webersta_re.htm", "Northern Colorado Bears": "https://college-football-results.com/f/z/nrthcolo_re.htm", "Portland State Vikings": "https://college-football-results.com/f/z/portland_re.htm", "Sacramento State Hornets": "https://college-football-results.com/f/z/sacramen_re.htm", "Idaho State Bengals": "https://college-football-results.com/f/z/idahosta_re.htm", "Idaho Vandals": "https://college-football-results.com/f/z/idaho_re.htm", "Tennessee State Tigers": "https://college-football-results.com/f/z/tennsta_re.htm", "Western Illinois Leathernecks": "https://college-football-results.com/f/z/westill_re.htm", "Lindenwood Lions": "https://college-football-results.com/f/z/lindenwo_re.htm", "Southeast Missouri Redhawks": "https://college-football-results.com/f/z/semisour_re.htm", "Gardner-Webb Bulldogs": "https://college-football-results.com/f/z/gardwebb_re.htm", "Eastern Illinois Panthers": "https://college-football-results.com/f/z/eastilli_re.htm", "Tennessee Tech Golden Eagles": "https://college-football-results.com/f/z/tenntech_re.htm", "Tennessee-Martin Skyhawks": "https://college-football-results.com/f/z/tnmartin_re.htm", "Charleston Southern Buccaneers": "https://college-football-results.com/f/z/charlsth_re.htm", "New Hampshire Wildcats": "https://college-football-results.com/f/z/newhamp_re.htm", "Villanova Wildcats": "https://college-football-results.com/f/z/villanov_re.htm", "Albany Great Danes": "https://college-football-results.com/f/z/albany_re.htm", "Monmouth Hawks": "https://college-football-results.com/f/z/monmouth_re.htm", "Elon Phoenix": "https://college-football-results.com/f/z/elon_re.htm", "North Carolina A&T Aggies": "https://college-football-results.com/f/z/ncarolat_re.htm", "Hampton Pirates": "https://college-football-results.com/f/z/hampton_re.htm", "William & Mary Tribe": "https://college-football-results.com/f/z/willmary_re.htm", "Towson Tigers": "https://college-football-results.com/f/z/towson_re.htm", "Stony Brook Seawolves": "https://college-football-results.com/f/z/stbrook_re.htm", "Bryant Bulldogs": "https://college-football-results.com/f/z/bryant_re.htm", "Maine Black Bears": "https://college-football-results.com/f/z/maine_re.htm", "Campbell Camels": "https://college-football-results.com/f/z/campbell_re.htm", "Rhode Island Rams": "https://college-football-results.com/f/z/rhodeisl_re.htm", "Merrimack Warriors": "https://college-football-results.com/f/z/merrimck_re.htm", "Sacred Heart Pioneers": "https://college-football-results.com/f/z/sacheart_re.htm", "Harvard Crimson": "https://college-football-results.com/f/z/harvard_re.htm", "Yale Bulldogs": "https://college-football-results.com/f/z/yale_re.htm", "Dartmouth Big Green": "https://college-football-results.com/f/z/dartmoth_re.htm", "Princeton Tigers": "https://college-football-results.com/f/z/princetn_re.htm", "Pennsylvania Quakers": "https://college-football-results.com/f/z/pennsylv_re.htm", "Cornell Big Red": "https://college-football-results.com/f/z/cornell_re.htm", "Brown Bears": "https://college-football-results.com/f/z/brown_re.htm", "Columbia Lions": "https://college-football-results.com/f/z/columbia_re.htm", "South Carolina State Bulldogs": "https://college-football-results.com/f/z/scarolst_re.htm", "North Carolina Central Eagles": "https://college-football-results.com/f/z/nccentrl_re.htm", "Morgan State Bears": "https://college-football-results.com/f/z/morganst_re.htm", "Norfolk State Spartans": "https://college-football-results.com/f/z/norfolk_re.htm", "Howard Bison": "https://college-football-results.com/f/z/howard_re.htm", "Delaware State Hornets": "https://college-football-results.com/f/z/delstate_re.htm", "North Dakota State Bison": "https://college-football-results.com/f/z/ndakotst_re.htm", "Northern Iowa Panthers": "https://college-football-results.com/f/z/nrthiowa_re.htm", "North Dakota Fighting Hawks": "https://college-football-results.com/f/z/ndakota_re.htm", "Youngstown State Penguins": "https://college-football-results.com/f/z/youngsta_re.htm", "South Dakota State Jackrabbits": "https://college-football-results.com/f/z/sdakotst_re.htm", "Illinois State Redbirds": "https://college-football-results.com/f/z/illstate_re.htm", "Murray State Racers": "https://college-football-results.com/f/z/murrayst_re.htm", "South Dakota Coyotes": "https://college-football-results.com/f/z/sdakota_re.htm", "Southern Illinois Salukis": "https://college-football-results.com/f/z/southill_re.htm", "Indiana State Sycamores": "https://college-football-results.com/f/z/indstate_re.htm", "Duquesne Dukes": "https://college-football-results.com/f/z/duquesne_re.htm", "Long Island Sharks": "https://college-football-results.com/f/z/lngislnd_re.htm", "Wagner Seahawks": "https://college-football-results.com/f/z/wagner_re.htm", "Mercyhurst Lakers": "https://college-football-results.com/f/z/mercyhst_re.htm", "Stonehill Skyhawks": "https://college-football-results.com/f/z/stonhill_re.htm", "Central Connecticut Blue Devils": "https://college-football-results.com/f/z/centconn_re.htm", "Robert Morris Colonials": "https://college-football-results.com/f/z/rmorris_re.htm", "St. Francis (PA) Red Flash": "https://college-football-results.com/f/z/stfrancs_re.htm", "Colgate Raiders": "https://college-football-results.com/f/z/colgate_re.htm", "Holy Cross Crusaders": "https://college-football-results.com/f/z/holycros_re.htm", "Lehigh Mountain Hawks": "https://college-football-results.com/f/z/lehigh_re.htm", "Fordham Rams": "https://college-football-results.com/f/z/fordham_re.htm", "Richmond Spiders": "https://college-football-results.com/f/z/richmond_re.htm", "Bucknell Bison": "https://college-football-results.com/f/z/bucknell_re.htm", "Georgetown Hoyas": "https://college-football-results.com/f/z/geortown_re.htm", "Lafayette Leopards": "https://college-football-results.com/f/z/lafaytte_re.htm", "Dayton Flyers": "https://college-football-results.com/f/z/dayton_re.htm", "St. Thomas (MN) Tommies": "https://college-football-results.com/f/z/sttommin_re.htm", "San Diego Toreros": "https://college-football-results.com/f/z/sandiego_re.htm", "Drake Bulldogs": "https://college-football-results.com/f/z/drake_re.htm", "Butler Bulldogs": "https://college-football-results.com/f/z/butler_re.htm", "Marist Red Foxes": "https://college-football-results.com/f/z/marist_re.htm", "Presbyterian Blue Hose": "https://college-football-results.com/f/z/presbytr_re.htm", "Valparaiso Beacons": "https://college-football-results.com/f/z/valpo_re.htm", "Morehead State Eagles": "https://college-football-results.com/f/z/morehead_re.htm", "Stetson Hatters": "https://college-football-results.com/f/z/stetson_re.htm", "Davidson Wildcats": "https://college-football-results.com/f/z/davidson_re.htm", "Furman Paladins": "https://college-football-results.com/f/z/furman_re.htm", "Wofford Terriers": "https://college-football-results.com/f/z/wofford_re.htm", "Mercer Bears": "https://college-football-results.com/f/z/mercer_re.htm", "Samford Bulldogs": "https://college-football-results.com/f/z/samford_re.htm", "Chattanooga Mocs": "https://college-football-results.com/f/z/chattano_re.htm", "East Tennessee Buccaneers": "https://college-football-results.com/f/z/easttenn_re.htm", "Citadel Bulldogs": "https://college-football-results.com/f/z/citadel_re.htm", "Western Carolina Catamounts": "https://college-football-results.com/f/z/wcarolin_re.htm", "Virginia Military Institute Keydets": "https://college-football-results.com/f/z/vmi_re.htm", "McNeese State Cowboys": "https://college-football-results.com/f/z/mcneese_re.htm", "East Texas A&M Lions": "https://college-football-results.com/f/z/commerce_re.htm", "Southeastern Louisiana Lions": "https://college-football-results.com/f/z/selouisi_re.htm", "Northwestern State Demons": "https://college-football-results.com/f/z/nwstate_re.htm", "Incarnate Word Cardinals": "https://college-football-results.com/f/z/incarnat_re.htm", "Stephen F. Austin Lumberjacks": "https://college-football-results.com/f/z/sfaustin_re.htm", "Lamar Cardinals": "https://college-football-results.com/f/z/lamar_re.htm", "Nicholls State Colonels": "https://college-football-results.com/f/z/nicholls_re.htm", "Houston Christian Huskies": "https://college-football-results.com/f/z/houbapts_re.htm", "Texas-Rio Grande Valley Vaqueros": "https://college-football-results.com/f/z/utrgvvaq_re.htm", "Florida A&M Rattlers": "https://college-football-results.com/f/z/floram_re.htm", "Grambling State Tigers": "https://college-football-results.com/f/z/gramblin_re.htm", "Southern Jaguars": "https://college-football-results.com/f/z/southern_re.htm", "Jackson State Tigers": "https://college-football-results.com/f/z/jacksons_re.htm", "Bethune-Cookman Wildcats": "https://college-football-results.com/f/z/bcookman_re.htm", "Alcorn State Braves": "https://college-football-results.com/f/z/alcornst_re.htm", "Alabama A&M Bulldogs": "https://college-football-results.com/f/z/alabamam_re.htm", "Alabama State Hornets": "https://college-football-results.com/f/z/alastate_re.htm", "Prairie View A&M Panthers": "https://college-football-results.com/f/z/prairiev_re.htm", "Arkansas-Pine Bluff Golden Lions": "https://college-football-results.com/f/z/pinebluf_re.htm", "Texas Southern Tigers": "https://college-football-results.com/f/z/texsouth_re.htm", "Mississippi Valley Delta Devils": "https://college-football-results.com/f/z/missvall_re.htm", "Eastern Kentucky Colonels": "https://college-football-results.com/f/z/eastkent_re.htm", "Central Arkansas Bears": "https://college-football-results.com/f/z/centrark_re.htm", "North Alabama Lions": "https://college-football-results.com/f/z/nalabama_re.htm", "Abilene Christian Wildcats": "https://college-football-results.com/f/z/abilene_re.htm", "Tarleton State Texans": "https://college-football-results.com/f/z/tarleton_re.htm", "Utah Tech Trailblazers": "https://college-football-results.com/f/z/dixiest_re.htm", "West Georgia Wolves": "https://college-football-results.com/f/z/wgeorgia_re.htm", "Southern Utah Thunderbirds": "https://college-football-results.com/f/z/sthnutah_re.htm", "Austin Peay Governors": "https://college-football-results.com/f/z/austpeay_re.htm"}