{"Albany Empire": "https://pro-football-results.com/afl/f/z/albempir_re.htm", "Philadelphia Soul": "https://pro-football-results.com/afl/f/z/philsoul_re.htm", "Baltimore Brigade": "https://pro-football-results.com/afl/f/z/baltbrid_re.htm", "Atlantic City Blackjacks": "https://pro-football-results.com/afl/f/z/atlacity_re.htm", "Washington Valor": "https://pro-football-results.com/afl/f/z/washvalr_re.htm", "Columbus Destroyers": "https://pro-football-results.com/afl/f/z/columbus_re.htm", "Iowa Barnstormers": "https://pro-football-results.com/afl/f/z/nydragon_re.htm", "Arizona Rattlers": "https://pro-football-results.com/afl/f/z/arizona_re.htm", "Massachusetts Marauders": "https://pro-football-results.com/afl/f/z/masschtt_re.htm", "San Jose Sabrecats": "https://pro-football-results.com/afl/f/z/sanjose_re.htm", "St. Louis Stampede": "https://pro-football-results.com/afl/f/z/stlouis_re.htm", "Orlando Predators": "https://pro-football-results.com/afl/f/z/orlando_re.htm", "Spokane Shock": "https://pro-football-results.com/afl/f/z/spokane_re.htm", "Chicago Rush": "https://pro-football-results.com/afl/f/z/chicrush_re.htm", "Jacksonville Sharks": "https://pro-football-results.com/afl/f/z/jcksnvil_re.htm", "Chicago Bruisers": "https://pro-football-results.com/afl/f/z/chicago_re.htm", "Tampa Bay Storm": "https://pro-football-results.com/afl/f/z/tampabay_re.htm", "Dallas Vigilantes": "https://pro-football-results.com/afl/f/z/dallvigl_re.htm", "Indiana Firebirds": "https://pro-football-results.com/afl/f/z/indiana_re.htm", "Denver Dynamite": "https://pro-football-results.com/afl/f/z/denver_re.htm", "Nashville Kats": "https://pro-football-results.com/afl/f/z/nashvill_re.htm", "Georgia Force": "https://pro-football-results.com/afl/f/z/georgia_re.htm", "Colorado Crush": "https://pro-football-results.com/afl/f/z/colcrush_re.htm", "San Antonio Talons": "https://pro-football-results.com/afl/f/z/tulsa_re.htm", "Los Angeles Avengers": "https://pro-football-results.com/afl/f/z/langeles_re.htm", "Pittsburgh Power": "https://pro-football-results.com/afl/f/z/ppower_re.htm", "Cleveland Gladiators": "https://pro-football-results.com/afl/f/z/lvglads_re.htm", "Dallas Texans": "https://pro-football-results.com/afl/f/z/daltexan_re.htm", "Austin Wranglers": "https://pro-football-results.com/afl/f/z/austin_re.htm", "Los Angeles Cobras": "https://pro-football-results.com/afl/f/z/lacobras_re.htm", "Utah Blaze": "https://pro-football-results.com/afl/f/z/uthblaze_re.htm", "Milwaukee Mustangs": "https://pro-football-results.com/afl/f/z/milwiron_re.htm", "Anaheim Piranhas": "https://pro-football-results.com/afl/f/z/anaheim_re.htm", "Grand Rapids Rampage": "https://pro-football-results.com/afl/f/z/grrapids_re.htm", "Cincinnati Rockers": "https://pro-football-results.com/afl/f/z/cincinna_re.htm", "Charlotte Rage": "https://pro-football-results.com/afl/f/z/charlott_re.htm", "Fort Worth Cavalry": "https://pro-football-results.com/afl/f/z/frtworth_re.htm", "Oklahoma City Yard Dawgs": "https://pro-football-results.com/afl/f/z/oklacity_re.htm", "Toronto Phantoms": "https://pro-football-results.com/afl/f/z/torphant_re.htm", "Detroit Fury": "https://pro-football-results.com/afl/f/z/detrfury_re.htm", "New Orleans VooDoo": "https://pro-football-results.com/afl/f/z/novoodoo_re.htm", "Oklahoma Wranglers": "https://pro-football-results.com/afl/f/z/oklahoma_re.htm", "Las Vegas Outlaws": "https://pro-football-results.com/afl/f/z/lvoutlaw_re.htm", "Florida Bobcats": "https://pro-football-results.com/afl/f/z/florida_re.htm", "Carolina Cobras": "https://pro-football-results.com/afl/f/z/carolina_re.htm", "Kansas City Command": "https://pro-football-results.com/afl/f/z/kcommand_re.htm", "Houston Thunderbears": "https://pro-football-results.com/afl/f/z/houston_re.htm", "Minnesota Fighting Pike": "https://pro-football-results.com/afl/f/z/minnsota_re.htm", "Los Angeles Kiss": "https://pro-football-results.com/afl/f/z/lakiss_re.htm", "New England Steamrollers": "https://pro-football-results.com/afl/f/z/nestroll_re.htm", "Portland Steel": "https://pro-football-results.com/afl/f/z/portthun_re.htm", "Washington Commandos": "https://pro-football-results.com/afl/f/z/washiton_re.htm", "New Orleans Night": "https://pro-football-results.com/afl/f/z/norleans_re.htm", "San Antonio Force": "https://pro-football-results.com/afl/f/z/santonio_re.htm", "Cleveland Thunderbolts": "https://pro-football-results.com/afl/f/z/clevland_re.htm", "New York Knights": "https://pro-football-results.com/afl/f/z/nyknight_re.htm", "Connecticut Coyotes": "https://pro-football-results.com/afl/f/z/conntcut_re.htm"}