{"Parma Panthers": "https://pro-football-results.com/nfle/f/z/parma_re.htm", "Varese Skorpions": "https://pro-football-results.com/nfle/f/z/varese_re.htm", "Firenze Guelfi": "https://pro-football-results.com/nfle/f/z/firenze_re.htm", "Milano Rhinos": "https://pro-football-results.com/nfle/f/z/milrhino_re.htm", "Ancona Dolphins": "https://pro-football-results.com/nfle/f/z/ancona_re.htm", "Bologna Warriors": "https://pro-football-results.com/nfle/f/z/bolowarr_re.htm", "Lazio Ducks": "https://pro-football-results.com/nfle/f/z/lazio_re.htm", "Torino Giaguari": "https://pro-football-results.com/nfle/f/z/torino_re.htm", "Legnano Frogs": "https://pro-football-results.com/nfle/f/z/legnano_re.htm", "Bergamo Lions": "https://pro-football-results.com/nfle/f/z/bergamo_re.htm", "Brescia Bengals": "https://pro-football-results.com/nfle/f/z/brescia_re.htm", "Busto Blue Storms": "https://pro-football-results.com/nfle/f/z/gorlamin_re.htm", "Modena Vipers": "https://pro-football-results.com/nfle/f/z/modena_re.htm", "Padova Saints": "https://pro-football-results.com/nfle/f/z/padovasa_re.htm", "Cecina Trappers": "https://pro-football-results.com/nfle/f/z/cecinatr_re.htm", "Savona Pirates": "https://pro-football-results.com/nfle/f/z/savona_re.htm", "Ferrara Aquile": "https://pro-football-results.com/nfle/f/z/ferrara_re.htm", "Cernusco Daemons": "https://pro-football-results.com/nfle/f/z/cernusco_re.htm", "Torino Reapers": "https://pro-football-results.com/nfle/f/z/torireap_re.htm", "Ravenna Chiefs": "https://pro-football-results.com/nfle/f/z/ravennac_re.htm", "Roma Grizzlies": "https://pro-football-results.com/nfle/f/z/romegriz_re.htm", "Verona Redskins": "https://pro-football-results.com/nfle/f/z/verona_re.htm", "Catania Elephants": "https://pro-football-results.com/nfle/f/z/catania_re.htm", "Bolzano Giants": "https://pro-football-results.com/nfle/f/z/blgiants_re.htm", "Pesaro Angels": "https://pro-football-results.com/nfle/f/z/pesaro_re.htm", "Trieste Mules": "https://pro-football-results.com/nfle/f/z/trieste_re.htm", "Milano Rams": "https://pro-football-results.com/nfle/f/z/milarams_re.htm", "Cagliari Crusaders": "https://pro-football-results.com/nfle/f/z/cagliari_re.htm", "Bologna Doves": "https://pro-football-results.com/nfle/f/z/boldoves_re.htm", "Roma Barbarians": "https://pro-football-results.com/nfle/f/z/romebarb_re.htm", "Milano Seamen (IFL)": "https://pro-football-results.com/nfle/f/z/seamen_re.htm", "Gallarate Kings": "https://pro-football-results.com/nfle/f/z/gallking_re.htm", "Milano Frogs": "https://pro-football-results.com/nfle/f/z/milfrogs_re.htm", "Udine Dragons": "https://pro-football-results.com/nfle/f/z/udine_re.htm", "Reggio Emilia Hogs": "https://pro-football-results.com/nfle/f/z/regemili_re.htm", "Verona Mastiffs": "https://pro-football-results.com/nfle/f/z/matini_re.htm", "Brugherio Falcons": "https://pro-football-results.com/nfle/f/z/brugheri_re.htm", "Palermo Corsairs": "https://pro-football-results.com/nfle/f/z/pcorsari_re.htm", "Rivoli Blackbills": "https://pro-football-results.com/nfle/f/z/rivoli_re.htm", "Sarzana Red Jackets": "https://pro-football-results.com/nfle/f/z/sarzana_re.htm", "Palermo Sharks": "https://pro-football-results.com/nfle/f/z/psharks_re.htm", "Roma Gladiators": "https://pro-football-results.com/nfle/f/z/romeglad_re.htm", "Roma Ducks": "https://pro-football-results.com/nfle/f/z/romeduck_re.htm", "Parma Bobcats": "https://pro-football-results.com/nfle/f/z/parmbobc_re.htm", "Grosseto Condors": "https://pro-football-results.com/nfle/f/z/grosseto_re.htm", "Naples Bandits": "https://pro-football-results.com/nfle/f/z/briganti_re.htm", "Romagna Titans": "https://pro-football-results.com/nfle/f/z/romagna_re.htm", "Trieste Mustangs": "https://pro-football-results.com/nfle/f/z/triemust_re.htm", "Alessandria Centurions": "https://pro-football-results.com/nfle/f/z/alessand_re.htm", "Taranto Dolphins": "https://pro-football-results.com/nfle/f/z/taranto_re.htm", "Salerno Seagulls": "https://pro-football-results.com/nfle/f/z/salerno_re.htm", "Livorno Etruscans": "https://pro-football-results.com/nfle/f/z/livorno_re.htm"}